mltrainer/__init__.py
mltrainer/imagemodels.py
mltrainer/metrics.py
mltrainer/preprocessors.py
mltrainer/rnn_models.py
mltrainer/settings.py
mltrainer/trainer.py
mltrainer/transformer.py
mltrainer/vae.py
mltrainer-0.2.5.dist-info/METADATA
mltrainer-0.2.5.dist-info/WHEEL
mltrainer-0.2.5.dist-info/RECORD
