Metadata-Version: 2.4
Name: mltrainer
Version: 0.2.5
Summary: toolkit for training pytorch models
Author-email: "R.Grouls" <Raoul.Grouls@han.nl>
License: MIT
Classifier: Development Status :: 4 - Beta
Classifier: Programming Language :: Python
Classifier: Topic :: Scientific/Engineering :: Artificial Intelligence
Classifier: Typing :: Typed
Requires-Python: <=3.12,>=3.11
Requires-Dist: loguru>=0.7.0
Requires-Dist: mlflow>=2.4.1
Requires-Dist: numpy>=1.25.0
Requires-Dist: psutil>=7.0.0
Requires-Dist: pydantic>=1.10.9
Requires-Dist: pytest-cov>=6.0.0
Requires-Dist: ray[tune]>=2.5.1
Requires-Dist: tensorboard>=2.18.0
Requires-Dist: tomlserializer>=0.1.0
Requires-Dist: torch-tb-profiler>=0.4.1
Requires-Dist: torch>=2.0.1
Requires-Dist: torchvision>=0.15.2
Requires-Dist: tqdm>=4.65.0
